ravioli/__init__.py
ravioli/__main__.py
ravioli/complexity.py
ravioli/function.py
ravioli/global_finder.py
ravioli/global_variable.py
ravioli/line_counter.py
ravioli/ravioli.py
ravioli/strip_comments.py
ravioli-0.3.0.dist-info/LICENSE
ravioli-0.3.0.dist-info/METADATA
ravioli-0.3.0.dist-info/WHEEL
ravioli-0.3.0.dist-info/entry_points.txt
ravioli-0.3.0.dist-info/top_level.txt
ravioli-0.3.0.dist-info/RECORD
