Metadata-Version: 2.1
Name: ravioli
Version: 0.3.0
Summary: Checks for spaghetti code
Home-page: https://github.com/ElectronVector/ravioli
Author: Matt Chernosky
Author-email: matt@electronvector.com
License: MIT
Platform: UNKNOWN
